tgwrapper/__init__.py
tgwrapper/tghelper.py
tgwrapper/tgwrapper.py
tgwrapper-0.1.5.dist-info/AUTHORS.rst
tgwrapper-0.1.5.dist-info/LICENSE
tgwrapper-0.1.5.dist-info/METADATA
tgwrapper-0.1.5.dist-info/WHEEL
tgwrapper-0.1.5.dist-info/entry_points.txt
tgwrapper-0.1.5.dist-info/top_level.txt
tgwrapper-0.1.5.dist-info/RECORD
