Metadata-Version: 2.1
Name: tgwrapper
Version: 0.1.5
Summary: Terragrunt wrapper for AWS infra deployment
Home-page: https://github.com/smruti-21/tgwrapper
Author: Smruti Sahoo
Author-email: ssahoo@mobiquityinc.com
License: MIT license
Keywords: tgwrapper
Platform: UNKNOWN
Classifier: Development Status :: 2 - Pre-Alpha
Classifier: Intended Audience :: Developers
Classifier: License :: OSI Approved :: MIT License
Classifier: Natural Language :: English
Classifier: Programming Language :: Python :: 3
Classifier: Programming Language :: Python :: 3.6
Classifier: Programming Language :: Python :: 3.7
Classifier: Programming Language :: Python :: 3.8
Requires-Python: >=3.6
Requires-Dist: Jinja2 (==2.11.3)
Requires-Dist: PyYAML (==5.4.1)
Requires-Dist: dpath (==2.0.1)
Requires-Dist: jinja2-ansible-filters (==1.3.0)
Requires-Dist: mergedeep (==1.3.4)
Requires-Dist: pytest (==6.2.2)
